{
  "id": "td_68b104ab",
  "source": "rss",
  "source_id": "https://techcrunch.com/?p=3110997",
  "source_url": "https://techcrunch.com/2026/04/09/meta-ai-app-climbs-to-no-5-on-the-app-store-after-muse-spark-launch/",
  "content_type": "article",
  "creator": {
    "id": "ai_news_&_artificial_intelligence_|_techcrunch",
    "name": "Sarah Perez",
    "handle": "AI News & Artificial Intelligence | TechCrunch",
    "platform": "rss",
    "follower_count": null,
    "is_tracked": true
  },
  "title": "Meta AI app climbs to No. 5 on the App Store after Muse Spark launch",
  "body_text": "The app was ranking No. 57 on the App Store just before Meta AI's new model launched. Now it's No. 5 — and rising.",
  "word_count": 24,
  "published_at": "2026-04-09T19:10:07.000Z",
  "ingested_at": "2026-04-10T11:00:13.492Z",
  "engagement": {
    "views": null,
    "likes": null,
    "replies": null,
    "reposts": null,
    "bookmarks": null,
    "engagement_rate": null
  },
  "tags": [
    "AI",
    "Apps",
    "Meta",
    "meta ai",
    "muse spark"
  ],
  "domain": "tech_startup",
  "language": "en",
  "media_duration_seconds": null,
  "distilled": false,
  "discourse_format": "news_article",
  "cited_creator_ids": []
}