{
  "id": "td_64996106",
  "source": "rss",
  "source_id": "https://gwern.substack.com/p/jan-2021-gwernnet-newsletter",
  "source_url": "https://gwern.substack.com/p/jan-2021-gwernnet-newsletter",
  "content_type": "article",
  "creator": {
    "id": "gwern.net_newsletter",
    "name": "gwern",
    "handle": "Gwern.net Newsletter",
    "platform": "rss",
    "follower_count": null,
    "is_tracked": true
  },
  "title": "Jan 2021 Gwern.net Newsletter",
  "body_text": "January 2021 gwern.net newsletter with links on AI scaling up and down.",
  "word_count": 12,
  "published_at": "2021-02-04T20:23:01.000Z",
  "ingested_at": "2026-03-28T13:00:12.442Z",
  "engagement": {
    "views": null,
    "likes": null,
    "replies": null,
    "reposts": null,
    "bookmarks": null,
    "engagement_rate": null
  },
  "tags": [],
  "domain": "tech_startup",
  "language": "en",
  "media_duration_seconds": 0,
  "distilled": true,
  "discourse_format": "news_article",
  "cited_creator_ids": []
}