{
  "id": "td_92efe171",
  "source": "rss",
  "source_id": "https://endpoints.news/?p=571630",
  "source_url": "https://endpoints.news/novartis-cuts-two-programs-in-cancer-related-blood-clots/",
  "content_type": "article",
  "creator": {
    "id": "endpoints_news",
    "name": "Nicole DeFeudis",
    "handle": "Endpoints News",
    "platform": "rss",
    "follower_count": null,
    "is_tracked": true
  },
  "title": "Novartis cuts two programs in cancer-related blood clots",
  "body_text": "Novartis has axed two late-stage programs in cancer-related blood clots after observing “inferior efficacy” in a clinical trial.\r\n\r\n The move marks a setback for a candidate that Novartis out-licensed in 2019, then",
  "word_count": 32,
  "published_at": "2026-04-20T18:24:47.000Z",
  "ingested_at": "2026-04-21T11:05:42.216Z",
  "engagement": {
    "views": null,
    "likes": null,
    "replies": null,
    "reposts": null,
    "bookmarks": null,
    "engagement_rate": null
  },
  "tags": [
    "R&D",
    "Pharma"
  ],
  "domain": "tech_startup",
  "language": "en",
  "media_duration_seconds": null,
  "distilled": false,
  "discourse_format": "news_article",
  "cited_creator_ids": []
}