{
  "id": "td_94957008",
  "source": "semantic_scholar",
  "source_id": "a34718fef883dccdd2cd4e5cc9847d6efd250473",
  "source_url": "https://www.semanticscholar.org/paper/a34718fef883dccdd2cd4e5cc9847d6efd250473",
  "content_type": "paper",
  "creator": {
    "id": "elliot_murphy",
    "name": "Elliot Murphy",
    "handle": "Elliot Murphy (neurolinguist)",
    "platform": "semantic_scholar",
    "follower_count": null,
    "is_tracked": true
  },
  "title": "Copy invisibility and (non-)categorial labeling",
  "body_text": "Copy invisibility and (non-)categorial labeling\nVenue: \nCitations: 9",
  "word_count": 8,
  "published_at": "2020-01-01T00:00:00Z",
  "ingested_at": "2026-03-26T20:28:16.743Z",
  "engagement": {
    "views": 9,
    "likes": 0,
    "replies": null,
    "reposts": null,
    "bookmarks": null,
    "engagement_rate": null
  },
  "tags": [
    "neurolinguistics",
    "language",
    "cognition"
  ],
  "domain": "tech_startup",
  "language": "en",
  "media_duration_seconds": null,
  "distilled": true,
  "discourse_format": "academic_paper"
}