{
  "id": "td_a020a453",
  "source": "rss",
  "source_id": "https://endpoints.news/?p=569852",
  "source_url": "https://endpoints.news/sanofi-bispecific-sails-through-asthma-sinusitis-trials-but-disappoints-in-eczema/",
  "content_type": "article",
  "creator": {
    "id": "endpoints_news",
    "name": "Ayisha Sharma",
    "handle": "Endpoints News",
    "platform": "rss",
    "follower_count": null,
    "is_tracked": true
  },
  "title": "Sanofi bispecific sails through asthma, sinusitis trials, but disappoints in eczema",
  "body_text": "Sanofi reported a mixed set of mid-stage data for its immunology drug that was designed to improve upon Dupixent and AstraZeneca’s Tezspire.\r\n\r\n The French drugmaker said Tuesday its bispecific nanobody, called ...",
  "word_count": 32,
  "published_at": "2026-04-07T10:44:28.000Z",
  "ingested_at": "2026-04-07T11:01:50.099Z",
  "engagement": {
    "views": null,
    "likes": null,
    "replies": null,
    "reposts": null,
    "bookmarks": null,
    "engagement_rate": null
  },
  "tags": [
    "R&D"
  ],
  "domain": "tech_startup",
  "language": "en",
  "media_duration_seconds": null,
  "distilled": false,
  "discourse_format": "news_article",
  "cited_creator_ids": []
}