{
  "id": "td_ba004cfb",
  "source": "github",
  "source_id": "darkrishabh/agent-skills-eval",
  "source_url": "https://github.com/darkrishabh/agent-skills-eval",
  "content_type": "repository",
  "creator": {
    "id": "darkrishabh",
    "name": "darkrishabh",
    "handle": "darkrishabh",
    "platform": "github",
    "follower_count": null,
    "is_tracked": false
  },
  "title": "darkrishabh/agent-skills-eval",
  "body_text": "# darkrishabh/agent-skills-eval\n\nA test runner for agentskills.io-style AI agent skills\n\nLanguage: TypeScript\nStars: 444\nForks: 16\nOwner: darkrishabh (User)\nCreated: 2026-05-06T05:10:29Z\nUpdated: 2026-05-12T09:46:29Z",
  "word_count": 23,
  "published_at": "2026-05-06T05:10:29Z",
  "ingested_at": "2026-05-12T11:02:48.752Z",
  "engagement": {
    "views": 444,
    "likes": 16,
    "replies": null,
    "reposts": null,
    "bookmarks": null,
    "engagement_rate": null
  },
  "tags": [
    "typescript"
  ],
  "domain": "tech_startup",
  "language": "en",
  "media_duration_seconds": null,
  "distilled": false,
  "discourse_format": "code_repository",
  "cited_creator_ids": []
}