{
  "id": "td_b5794442",
  "source": "rss",
  "source_id": "https://news.ycombinator.com/item?id=47743730",
  "source_url": "https://bsky.app/profile/serenityforge.com/post/3mj3r4nbiws2t",
  "content_type": "article",
  "creator": {
    "id": "hacker_news:_best",
    "name": "super256",
    "handle": "Hacker News: Best",
    "platform": "rss",
    "follower_count": null,
    "is_tracked": true
  },
  "title": "Google removes \"Doki Doki Literature Club\" from Google Play",
  "body_text": "Article URL: https://bsky.app/profile/serenityforge.com/post/3mj3r4nbiws2t\nComments URL: https://news.ycombinator.com/item?id=47743730\nPoints: 465\n# Comments: 234",
  "word_count": 11,
  "published_at": "2026-04-12T19:53:08.000Z",
  "ingested_at": "2026-04-13T11:00:15.257Z",
  "engagement": {
    "views": null,
    "likes": null,
    "replies": null,
    "reposts": null,
    "bookmarks": null,
    "engagement_rate": null
  },
  "tags": [],
  "domain": "tech_startup",
  "language": "en",
  "media_duration_seconds": null,
  "distilled": false,
  "discourse_format": "news_article",
  "cited_creator_ids": []
}