{
  "id": "td_d62f6661",
  "source": "semantic_scholar",
  "source_id": "66de67f9e370350eeeca48259ee92eab5db5664c",
  "source_url": "https://www.semanticscholar.org/paper/66de67f9e370350eeeca48259ee92eab5db5664c",
  "content_type": "paper",
  "creator": {
    "id": "elliot_murphy",
    "name": "Elliot Murphy",
    "handle": "Elliot Murphy (neurolinguist)",
    "platform": "semantic_scholar",
    "follower_count": null,
    "is_tracked": true
  },
  "title": "The Oscillopathic Nature of Language Deficits in Autism: From Genes to Language Evolution",
  "body_text": "The Oscillopathic Nature of Language Deficits in Autism: From Genes to Language Evolution\nAutism spectrum disorders (ASD) are pervasive neurodevelopmental disorders involving a number of deficits to linguistic cognition. The gap between genetics and the pathophysiology of ASD remains open, in particular regarding its distinctive linguistic profile. The goal of this article is to attempt to bridge this gap, focusing on how the autistic brain processes language, particularly through the perspective of brain rhythms. Due to the phenomenon of pleiotropy, which may take some decades to overcome, we believe that studies of brain rhythms, which are not faced with problems of this scale, may constitute a more tractable route to interpreting language deficits in ASD and eventually other neurocognitive disorders. Building on recent attempts to link neural oscillations to certain computational primitives of language, we show that interpreting language deficits in ASD as oscillopathic traits is a potentially fruitful way to construct successful endophenotypes of this condition. Additionally, we will show that candidate genes for ASD are overrepresented among the genes that played a role in the evolution of language. These genes include (and are related to) genes involved in brain rhythmicity. We hope that the type of steps taken here will additionally lead to a better understanding of the comorbidity, heterogeneity, and variability of ASD, and may help achieve a better treatment of the affected populations.\nVenue: Frontiers in Human Neuroscience\nCitations: 69",
  "word_count": 234,
  "published_at": "2016-03-18",
  "ingested_at": "2026-03-26T20:28:16.746Z",
  "engagement": {
    "views": 69,
    "likes": 2,
    "replies": null,
    "reposts": null,
    "bookmarks": null,
    "engagement_rate": null
  },
  "tags": [
    "neurolinguistics",
    "language",
    "cognition"
  ],
  "domain": "tech_startup",
  "language": "en",
  "media_duration_seconds": null,
  "distilled": true,
  "discourse_format": "academic_paper"
}