{
  "id": "td_df489a2f",
  "source": "arxiv",
  "source_id": "2604.02324",
  "source_url": "https://arxiv.org/abs/2604.02324",
  "content_type": "paper",
  "creator": {
    "id": "daiwei_chen",
    "name": "Daiwei Chen",
    "handle": "Daiwei Chen, Zhoutong Fu, Chengming Jiang, Haichao Zhang, Ran Zhou, Tan Wang, Chunnan Yao, Guoyao Li, Rui Cai, Yihan Cao, Ruijie Jiang, Fedor Borisyuk, Jianqiang Shen, Jingwei Wu, Ramya Korlakai Vinayak",
    "platform": "arxiv",
    "follower_count": null,
    "is_tracked": false
  },
  "title": "Grounded Token Initialization for New Vocabulary in LMs for Generative Recommendation",
  "body_text": "Grounded Token Initialization for New Vocabulary in LMs for Generative Recommendation\n\nLanguage models (LMs) are increasingly extended with new learnable vocabulary tokens for domain-specific tasks, such as Semantic-ID tokens in generative recommendation. The standard practice initializes these new tokens as the mean of existing vocabulary embeddings, then relies on supervised fine-tuning to learn their representations. We present a systematic analysis of this strategy: through spectral and geometric diagnostics, we show that mean initialization collapses all new tokens into a degenerate subspace, erasing inter-token distinctions that subsequent fine-tuning struggles to fully recover. These findings suggest that \\emph{token initialization} is a key bottleneck when extending LMs with new vocabularies. Motivated by this diagnosis, we propose the \\emph{Grounded Token Initialization Hypothesis}: linguistically grounding novel tokens in the pretrained embedding space before fine-tuning better enables the model to leverage its general-purpose knowledge for novel-token domains. We operationalize this hypothesis as GTI (Grounded Token Initialization), a lightweight grounding stage that, prior to fine-tuning, maps new tokens to distinct, semantically meaningful locations in the pretrained embedding space using only paired linguistic supervision. Despite its simplicity, GTI outperforms both mean initialization and existing auxiliary-task adaptation methods in the majority of evaluation settings across multiple generative recommendation benchmarks, including industry-scale and public datasets. Further analyses show that grounded embeddings produce richer inter-token structure that persists through fine-tuning, corroborating the hypothesis that initialization quality is a key bottleneck in vocabulary extension.\n\nAuthors: Daiwei Chen, Zhoutong Fu, Chengming Jiang, Haichao Zhang, Ran Zhou, Tan Wang, Chunnan Yao, Guoyao Li, Rui Cai, Yihan Cao, Ruijie Jiang, Fedor Borisyuk, Jianqiang Shen, Jingwei Wu, Ramya Korlakai Vinayak\nCategories: cs.CL, cs.AI, cs.LG, cs.CL",
  "word_count": 221,
  "published_at": "2026-04-02T17:59:19Z",
  "ingested_at": "2026-04-04T04:32:51.602Z",
  "engagement": {
    "views": null,
    "likes": null,
    "replies": null,
    "reposts": null,
    "bookmarks": null,
    "engagement_rate": null
  },
  "tags": [
    "cs.CL",
    "cs.AI",
    "cs.LG",
    "cs.CL"
  ],
  "domain": "tech_ai",
  "language": "en",
  "media_duration_seconds": null,
  "distilled": true,
  "discourse_format": "academic_paper",
  "cited_creator_ids": []
}