{
  "id": "td_f104b3a6",
  "source": "github",
  "source_id": "mattpocock/dictionary-of-ai-coding",
  "source_url": "https://github.com/mattpocock/dictionary-of-ai-coding",
  "content_type": "repository",
  "creator": {
    "id": "mattpocock",
    "name": "mattpocock",
    "handle": "mattpocock",
    "platform": "github",
    "follower_count": null,
    "is_tracked": false
  },
  "title": "mattpocock/dictionary-of-ai-coding",
  "body_text": "# mattpocock/dictionary-of-ai-coding\n\nAI coding jargon, explained in plain English.\n\nLanguage: TypeScript\nStars: 522\nForks: 88\nOwner: mattpocock (User)\nCreated: 2026-05-01T10:17:05Z\nUpdated: 2026-05-02T10:58:58Z",
  "word_count": 22,
  "published_at": "2026-05-01T10:17:05Z",
  "ingested_at": "2026-05-02T11:02:13.009Z",
  "engagement": {
    "views": 522,
    "likes": 88,
    "replies": null,
    "reposts": null,
    "bookmarks": null,
    "engagement_rate": null
  },
  "tags": [
    "typescript"
  ],
  "domain": "tech_startup",
  "language": "en",
  "media_duration_seconds": null,
  "distilled": false,
  "discourse_format": "code_repository",
  "cited_creator_ids": []
}